partnersimulator/__init__.py
partnersimulator/bomb.py
partnersimulator/partnerconstructor.py
partnersimulator-0.0.5.dist-info/METADATA
partnersimulator-0.0.5.dist-info/WHEEL
partnersimulator-0.0.5.dist-info/top_level.txt
partnersimulator-0.0.5.dist-info/RECORD
