Metadata-Version: 2.4
Name: partnersimulator
Version: 0.0.5
Summary: Partner Simulator
Author: Aditya Jain
Author-email: aditya.jain22@imperial.ac.uk
Keywords: creepy,parasocial
Classifier: Development Status :: 3 - Alpha
Classifier: Intended Audience :: Education
Classifier: Programming Language :: Python :: 2
Classifier: Programming Language :: Python :: 3
Classifier: Operating System :: MacOS :: MacOS X
Classifier: Operating System :: Microsoft :: Windows
Requires-Dist: openai
Requires-Dist: polars
Dynamic: author
Dynamic: author-email
Dynamic: classifier
Dynamic: description
Dynamic: description-content-type
Dynamic: keywords
Dynamic: requires-dist
Dynamic: summary
